bumblebee_status/__init__.py
bumblebee_status/_version.py
bumblebee_status/discover.py
bumblebee_status/core/__init__.py
bumblebee_status/core/config.py
bumblebee_status/core/decorators.py
bumblebee_status/core/event.py
bumblebee_status/core/input.py
bumblebee_status/core/module.py
bumblebee_status/core/output.py
bumblebee_status/core/theme.py
bumblebee_status/core/widget.py
bumblebee_status/modules/__init__.py
bumblebee_status/modules/contrib/__init__.py
bumblebee_status/modules/contrib/aerlive.py
bumblebee_status/modules/contrib/amixer.py
bumblebee_status/modules/contrib/apt.py
bumblebee_status/modules/contrib/arandr.py
bumblebee_status/modules/contrib/arch-update.py
bumblebee_status/modules/contrib/arch_update.py
bumblebee_status/modules/contrib/aur-update.py
bumblebee_status/modules/contrib/battery-upower.py
bumblebee_status/modules/contrib/battery.py
bumblebee_status/modules/contrib/battery_upower.py
bumblebee_status/modules/contrib/bluetooth.py
bumblebee_status/modules/contrib/bluetooth2.py
bumblebee_status/modules/contrib/blugon.py
bumblebee_status/modules/contrib/brightness.py
bumblebee_status/modules/contrib/caffeine.py
bumblebee_status/modules/contrib/calendar.py
bumblebee_status/modules/contrib/cmus.py
bumblebee_status/modules/contrib/cpu2.py
bumblebee_status/modules/contrib/cpu3.py
bumblebee_status/modules/contrib/currency.py
bumblebee_status/modules/contrib/datetimetz.py
bumblebee_status/modules/contrib/datetz.py
bumblebee_status/modules/contrib/deadbeef.py
bumblebee_status/modules/contrib/deezer.py
bumblebee_status/modules/contrib/dnf.py
bumblebee_status/modules/contrib/docker_ps.py
bumblebee_status/modules/contrib/dunst.py
bumblebee_status/modules/contrib/dunstctl.py
bumblebee_status/modules/contrib/emerge_status.py
bumblebee_status/modules/contrib/epoch.py
bumblebee_status/modules/contrib/gcalendar.py
bumblebee_status/modules/contrib/getcrypto.py
bumblebee_status/modules/contrib/github.py
bumblebee_status/modules/contrib/gitlab.py
bumblebee_status-2.3.0.dist-info/licenses/LICENSE
bumblebee_status-2.3.0.dist-info/METADATA
bumblebee_status-2.3.0.dist-info/WHEEL
bumblebee_status-2.3.0.dist-info/top_level.txt
bumblebee_status-2.3.0.dist-info/RECORD
