Metadata-Version: 2.4
Name: bumblebee-status
Version: 2.3.0
Summary: a modular, theme-able status line generator for the i3 window manager.
Home-page: https://github.com/tobi-wan-kenobi/bumblebee-status
Author: tobi-wan-kenobi
Author-email: github@tobi-wan-kenobi.at
License: MIT
Project-URL: Documentation, https://bumblebee-status.readthedocs.io/
Project-URL: Code, https://github.com/tobi-wan-kenobi/bumblebee-status
Project-URL: Issue tracker, https://github.com/tobi-wan-kenobi/bumblebee-status
Keywords: bumblebee-status
Classifier: Development Status :: 3 - Alpha
Classifier: License :: OSI Approved :: MIT License
Classifier: Intended Audience :: Developers
Classifier: Programming Language :: Python
Classifier: Programming Language :: Python :: 3
Classifier: Programming Language :: Python :: 3.4
Classifier: Programming Language :: Python :: 3.5
Classifier: Programming Language :: Python :: 3.6
Classifier: Programming Language :: Python :: 3.7
Classifier: Programming Language :: Python :: 3.8
Classifier: Programming Language :: Python :: 3.9
Classifier: Topic :: Software Development :: Libraries
Classifier: Topic :: Software Development :: Internationalization
Classifier: Topic :: Utilities
License-File: LICENSE
Provides-Extra: battery-upower
Requires-Dist: dbus-python; extra == "battery-upower"
Requires-Dist: power; extra == "battery-upower"
Provides-Extra: cpu
Requires-Dist: psutil; extra == "cpu"
Provides-Extra: cpu2
Requires-Dist: psutil; extra == "cpu2"
Provides-Extra: currency
Requires-Dist: requests; extra == "currency"
Requires-Dist: Babel; extra == "currency"
Provides-Extra: docker-ps
Requires-Dist: docker; extra == "docker-ps"
Provides-Extra: getcrypto
Requires-Dist: requests; extra == "getcrypto"
Provides-Extra: git
Requires-Dist: pygit2; extra == "git"
Provides-Extra: github
Requires-Dist: requests; extra == "github"
Provides-Extra: layout-xkb
Requires-Dist: xkbgroup; extra == "layout-xkb"
Provides-Extra: memory
Requires-Dist: psutil; extra == "memory"
Provides-Extra: network-traffic
Requires-Dist: psutil; extra == "network-traffic"
Requires-Dist: netifaces; extra == "network-traffic"
Provides-Extra: nic
Requires-Dist: netifaces; extra == "nic"
Provides-Extra: pihole
Requires-Dist: requests; extra == "pihole"
Provides-Extra: rss
Requires-Dist: feedparser; extra == "rss"
Provides-Extra: spaceapi
Requires-Dist: requests; extra == "spaceapi"
Provides-Extra: spotify
Requires-Dist: dbus-python; extra == "spotify"
Provides-Extra: stock
Requires-Dist: requests; extra == "stock"
Provides-Extra: sun
Requires-Dist: requests; extra == "sun"
Requires-Dist: suntime; extra == "sun"
Provides-Extra: system
Requires-Dist: Pillow; extra == "system"
Provides-Extra: taskwarrior
Requires-Dist: taskw; extra == "taskwarrior"
Provides-Extra: title
Requires-Dist: i3ipc; extra == "title"
Provides-Extra: traffic
Requires-Dist: psutil; extra == "traffic"
Requires-Dist: netifaces; extra == "traffic"
Provides-Extra: weather
Requires-Dist: requests; extra == "weather"
Provides-Extra: yubikey
Requires-Dist: python-yubico; extra == "yubikey"
Dynamic: license-file
Dynamic: provides-extra
